cj/__init__.py
cj/cj_ranking.py
cj/models/BTM.py
cj/models/BayesianCJ.py
cj/models/__init__.py
cj/pair_selector/__init__.py
cj/pair_selector/entropy.py
cj/pair_selector/random.py
comparative_judgement-0.0.7.dist-info/METADATA
comparative_judgement-0.0.7.dist-info/WHEEL
comparative_judgement-0.0.7.dist-info/top_level.txt
comparative_judgement-0.0.7.dist-info/RECORD
